pylovelace/kernel/__init__.py
pylovelace/kernel/lovelace.pyd
pylovelace/kernel/lovelace.so
pylovelace.kernel-2023.3.0.dist-info/METADATA
pylovelace.kernel-2023.3.0.dist-info/WHEEL
pylovelace.kernel-2023.3.0.dist-info/top_level.txt
pylovelace.kernel-2023.3.0.dist-info/RECORD
