Metadata-Version: 2.1
Name: pylovelace.kernel
Version: 2023.3.0
Summary: PyLovelace Kernel
Author: nshout
Requires-Python: >=3.10, <3.13
